protollm/.DS_Store
protollm/__init__.py
protollm/agents/README.md
protollm/agents/__init__.py
protollm/agents/agent_prompts.py
protollm/agents/agent_utils/parsers.py
protollm/agents/agent_utils/prompt_utils.py
protollm/agents/agent_utils/pydantic_models.py
protollm/agents/agent_utils/states.py
protollm/agents/builder.py
protollm/agents/llama31_agents/__init__.py
protollm/agents/llama31_agents/llama31_agent.py
protollm/agents/universal_agents.py
protollm/connectors/README.md
protollm/connectors/__init__.py
protollm/connectors/connector_creator.py
protollm/connectors/rest_server.py
protollm/connectors/utils.py
protollm/definitions.py
protollm/ensembles_ma/collect_results.py
protollm/metrics/__init__.py
protollm/metrics/deepeval_connector.py
protollm/metrics/evaluation_metrics.py
protollm/rags/__init__.py
protollm/rags/configs/chroma.env
protollm/rags/configs/docs_processing_config.yaml
protollm/rags/configs/elastic.env
protollm/rags/jobs.py
protollm/rags/pipeline/__init__.py
protollm/rags/pipeline/docs_processing/__init__.py
protollm/rags/pipeline/docs_processing/entities.py
protollm/rags/pipeline/docs_processing/exceptions.py
protollm/rags/pipeline/docs_processing/models.py
protollm/rags/pipeline/docs_processing/utils.py
protollm/rags/pipeline/etl_pipeline.py
protollm/rags/rag_core/__init__.py
protollm/rags/rag_core/planner.py
protollm/rags/rag_core/reranker.py
protollm/rags/rag_core/retriever.py
protollm/rags/rag_core/utils.py
protollm/rags/settings/__init__.py
protollm/rags/settings/chroma_settings.py
protollm/rags/settings/es_settings.py
protollm/rags/settings/pipeline_settings.py
protollm/rags/stores/__init__.py
protollm/rags/stores/chroma/__init__.py
protollm/rags/stores/chroma/chroma_loader.py
protollm/rags/stores/chroma/utils.py
protollm/rags/stores/elasticsearch/__init__.py
protollm/rags/stores/elasticsearch/configs/index_mappings.json
protollm/rags/stores/elasticsearch/configs/index_settings.json
protollm-0.1.6.dist-info/METADATA
protollm-0.1.6.dist-info/WHEEL
protollm-0.1.6.dist-info/licenses/LICENSE
protollm-0.1.6.dist-info/RECORD
