Metadata-Version: 2.4
Name: ProtoLLM
Version: 0.1.6
Summary: A library with which to prototype LLM-based applications quickly and easily.
License-Expression: BSD-3-Clause
License-File: LICENSE
Author: aimclub
Author-email: aim.club@itmo.ru
Requires-Python: >=3.10,<4.0
Classifier: Programming Language :: Python :: 3
Classifier: Programming Language :: Python :: 3.10
Classifier: Programming Language :: Python :: 3.11
Classifier: Programming Language :: Python :: 3.12
Classifier: Programming Language :: Python :: 3.13
Classifier: Programming Language :: Python :: 3.14
Requires-Dist: aioredis (>=2.0.1,<3.0.0)
Requires-Dist: celery (>=5.4.0,<6.0.0)
Requires-Dist: chardet (>=5.2.0)
Requires-Dist: chromadb (>=1.0.0)
Requires-Dist: click (>=8.2.0)
Requires-Dist: deepeval (>=3.4.0)
Requires-Dist: fastapi (>=0.119.0)
Requires-Dist: flower (>=2.0.1,<3.0.0)
Requires-Dist: ftfy (>=6.3.1)
Requires-Dist: httpx (>=0.28.1)
Requires-Dist: kombu (>=5.3.7,<6.0.0)
Requires-Dist: langchain (>=0.3.6,<1.0.0)
Requires-Dist: langchain-chroma (>=0.2.0,<1.0.0)
Requires-Dist: langchain-community (>=0.3.10,<0.4.0)
Requires-Dist: langchain-core (>=0.3.50,<1.0.0)
Requires-Dist: langchain-elasticsearch (>=0.3.2)
Requires-Dist: langchain-gigachat (>=0.3.12)
Requires-Dist: langchain-ollama (>=0.3.0,<1.0.0)
Requires-Dist: langchain-openai (>=0.3.10,<1.0.0)
Requires-Dist: langchain-text-splitters (>=0.3.3,<1.0.0)
Requires-Dist: langgraph (>=1.0.0)
Requires-Dist: numpy (>=2.1.0)
Requires-Dist: openai (>=2.6.0)
Requires-Dist: pandas (>=2.2.3,<3.0.0)
Requires-Dist: pdf2image (>=1.17.0)
Requires-Dist: pdfminer.six (>=20231228)
Requires-Dist: pdfplumber (>=0.11.5)
Requires-Dist: pika (>=1.3.2,<2.0.0)
Requires-Dist: pillow (>=11.1.0)
Requires-Dist: pydantic (>=2.12.0)
Requires-Dist: pydantic-core (>=2.41.0)
Requires-Dist: pydantic-settings (>=2.10.0)
Requires-Dist: pypdf2 (>=3.0.1)
Requires-Dist: pytesseract (>=0.3.13)
Requires-Dist: python-docx (>=1.1.2)
Requires-Dist: python-dotenv (>=1.0.1)
Requires-Dist: pyyaml (>=6.0.2)
Requires-Dist: redis (>=6.4.0)
Requires-Dist: requests (>=2.32.3)
Requires-Dist: spacy (>=3.8.0)
Requires-Dist: tabulate (>=0.9.0)
Requires-Dist: tornado (>=6.4.1,<7.0.0)
Requires-Dist: tqdm (>=4.67.1)
Requires-Dist: transformers (>=4.57.1)
Requires-Dist: urllib3 (>=2.2.2)
Requires-Dist: uuid (>=1.30)
Requires-Dist: websockets (>=14.1)
Project-URL: Homepage, https://github.com/aimclub/ProtoLLM
Project-URL: Issues, https://github.com/aimclub/ProtoLLM/issues
